circleci_audit/__init__.py
circleci_audit/circleci.py
circleci_audit/cli.py
circleci_audit/config.py
circleci_audit/contexts.py
circleci_audit/known_error.py
circleci_audit/main.py
circleci_audit/organizations.py
circleci_audit/repositories.py
circleci_audit-1.0.1.dist-info/LICENSE.txt
circleci_audit-1.0.1.dist-info/METADATA
circleci_audit-1.0.1.dist-info/WHEEL
circleci_audit-1.0.1.dist-info/entry_points.txt
circleci_audit-1.0.1.dist-info/top_level.txt
circleci_audit-1.0.1.dist-info/RECORD
