Metadata-Version: 2.1
Name: circleci-audit
Version: 1.0.1
Summary: A package for auditing CircleCI
Author-email: Rupert Madden-Abbott <rupert.madden.abbott@gmail.com>
Project-URL: Homepage, https://github.com/rupert-madden-abbott/circleci-audit
Project-URL: Bug Tracker, https://github.com/rupert-madden-abbott/circleci-audit/issues
Classifier: Programming Language :: Python :: 3
Classifier: License :: OSI Approved :: MIT License
Classifier: Operating System :: OS Independent
Requires-Python: >=3.7
License-File: LICENSE.txt
